wads/__init__.py
wads/ci_config.py
wads/ci_migration.py
wads/config_comparison.py
wads/generate_project_wheels.py
wads/github_ci_ops.py
wads/install_system_deps.py
wads/licensing.py
wads/migration.py
wads/migration_quick_ref.py
wads/pack.py
wads/package_module.py
wads/populate.py
wads/setup_utils.py
wads/toml_util.py
wads/trans.py
wads/util.py
wads/agents/README.md
wads/agents/__init__.py
wads/agents/ci_debug_agent.py
wads/agents/dependency_resolver.py
wads/agents/test_analyzer.py
wads/data/.editorconfig_tpl
wads/data/.gitattributes_tpl
wads/data/.gitignore_tpl
wads/data/MANIFEST.in
wads/data/bug_report_tpl.md
wads/data/dependabot_tpl.yml
wads/data/feature_request_tpl.md
wads/data/github_ci_publish_2025.yml
wads/data/github_ci_tpl_deploy.yml
wads/data/github_ci_tpl_publish.yml
wads/data/github_licenses.json
wads/data/gitlab_ci_tpl.yml
wads/data/pull_request_template_tpl.md
wads/data/pyproject_toml_tpl.toml
wads/data/setup_tpl
wads/data/wads_operational_dependencies.yml
wads/examples/migration_example.py
wads/examples/real_project_migration.py
wads/scrap/__init__.py
wads/scrap/handle_non_python_installs.py
wads/scripts/README.md
wads/scripts/__init__.py
wads/scripts/build_dist.py
wads/scripts/install_deps.py
wads/scripts/read_ci_config.py
wads/scripts/set_env_vars.py
wads/scripts/validate_ci_env.py
wads/tests/__init__.py
wads/tests/conftest.py
wads/tests/test_action_definitions.py
wads/tests/test_config_comparison.py
wads/tests/test_migration.py
wads/tests/test_populate_and_pack.py
wads/tests/test_script_cli.py
wads/tests/test_scripts.py
wads/tests/test_workflow_template.py
wads/tests/data/__init__.py
wads/tests/data/example.json
wads/tests/data/example.pkl
wads/tests/data/example_module.py
wads-0.1.64.dist-info/METADATA
wads-0.1.64.dist-info/WHEEL
wads-0.1.64.dist-info/entry_points.txt
wads-0.1.64.dist-info/licenses/LICENSE
wads-0.1.64.dist-info/RECORD
