Metadata-Version: 2.4
Name: wads
Version: 0.1.64
Summary: Tools for packaging and publishing to pypi for those who just do not want to deal with it
Project-URL: Homepage, https://github.com/i2mint/wads
Author: Thor Whalen
License: Apache Software License
License-File: LICENSE
Keywords: documentation,packaging,publishing
Requires-Python: >=3.10
Requires-Dist: argh
Requires-Dist: build
Requires-Dist: packaging
Requires-Dist: pylint
Requires-Dist: pytest
Requires-Dist: pyyaml
Requires-Dist: requests
Requires-Dist: ruamel-yaml
Requires-Dist: tomli-w>=0.4.0
Requires-Dist: tomli>=1.0.0; python_version < '3.11'
Requires-Dist: wheel
Provides-Extra: docs
Requires-Dist: epythet; extra == 'docs'
Provides-Extra: setuptools
Requires-Dist: setuptools>=65.0.0; extra == 'setuptools'
